deepgraph/_find_selected_indices.pyx
deepgraph/deepgraph.py
deepgraph/connectors_and_selectors.py
deepgraph/iterators_and_indexers.py
deepgraph/_find_selected_indices.pypy310-pp73-darwin.so
deepgraph/__init__.py
deepgraph/utils.py
deepgraph/_triu_indices.pypy310-pp73-darwin.so
deepgraph/connector_selector_implementations.py
deepgraph/_find_selected_indices.c
deepgraph/_triu_indices.pyx
deepgraph/_triu_indices.c
deepgraph-1.2.0.dist-info/RECORD
deepgraph-1.2.0.dist-info/WHEEL
deepgraph-1.2.0.dist-info/top_level.txt
deepgraph-1.2.0.dist-info/METADATA
deepgraph-1.2.0.dist-info/licenses/LICENSE
