Metadata-Version: 2.4
Name: deepgraph
Version: 1.2.0
Summary: Analyze Data with Pandas-based Networks.
Author-email: Dominik Traxl <dominik.traxl@posteo.org>
License-Expression: BSD-3-Clause
Project-URL: Homepage, https://github.com/deepgraph/deepgraph/
Project-URL: Documentation, https://deepgraph.readthedocs.io
Project-URL: Repository, https://github.com/deepgraph/deepgraph/
Classifier: Operating System :: OS Independent
Classifier: Programming Language :: Python :: 3
Classifier: Programming Language :: Cython
Classifier: Topic :: Software Development :: Libraries :: Python Modules
Classifier: Topic :: Scientific/Engineering :: Information Analysis
Classifier: Topic :: Scientific/Engineering :: Mathematics
Classifier: Topic :: Scientific/Engineering :: Physics
Requires-Python: >=3.9
License-File: LICENSE
Requires-Dist: numpy>=1.21.6
Requires-Dist: pandas>=1.2
Provides-Extra: plot
Requires-Dist: matplotlib>=3.1; extra == "plot"
Provides-Extra: basemap
Requires-Dist: basemap>=2.0; extra == "basemap"
Provides-Extra: tables
Requires-Dist: tables>=3.7; extra == "tables"
Provides-Extra: scipy
Requires-Dist: scipy>=1.5.4; extra == "scipy"
Provides-Extra: networkx
Requires-Dist: networkx>=2.4; extra == "networkx"
Provides-Extra: all
Requires-Dist: matplotlib>=3.1; extra == "all"
Requires-Dist: basemap>=2.0; extra == "all"
Requires-Dist: tables>=3.7; extra == "all"
Requires-Dist: scipy>=1.5.4; extra == "all"
Requires-Dist: networkx>=2.4; extra == "all"
Dynamic: license-file
